kompozitor/__init__.py
kompozitor-0.0.1.dist-info/METADATA
kompozitor-0.0.1.dist-info/WHEEL
kompozitor-0.0.1.dist-info/license.txt
kompozitor-0.0.1.dist-info/top_level.txt
kompozitor-0.0.1.dist-info/RECORD
